{
"/": {
    "controller": "DashBoardController",
    "action": "dashBoard"
},
"/logout": {
    "controller": "LoginController",
    "action": "logout"
},
"/profile": {
    "controller": "LoginController",
    "action": "loginAttempt"
},
"/insert": {
    "controller": "InsertController",
    "action": "insertPedidos"
},
"/edit": {
    "controller": "EditController",
    "action": "editPedidos"
},
"/update": {
    "controller": "EditController",
    "action": "updatePedidos"
},
"/delete": {
    "controller": "EditController",
    "action": "deletePedidos"
},
"/productos": {
    "controller": "ProductosController",
    "action": "showProductos"
},
"/pedidos": {
    "controller": "PedidosController",
    "action": "showPedidos"
},
"/empleados": {
    "controller": "EmpleadosController",
    "action": "showEmpleados"
},
"/clientes": {
    "controller": "ClientesController",
    "action": "showClientes"
},
"/detalle": {
    "controller": "DetallesController",
    "action": "showDetalles"
},
"/showDetalle": {
    "controller": "EditController",
    "action": "showPedidos"
}
}